moon_engine/__init__.py
moon_engine/__main__.py
moon_engine/authz_driver.py
moon_engine/orchestration_driver.py
moon_engine/server.py
moon_engine/api/__init__.py
moon_engine/api/configuration.py
moon_engine/api/import_json.py
moon_engine/api/logs.py
moon_engine/api/status.py
moon_engine/api/authz/__init__.py
moon_engine/api/authz/authz.py
moon_engine/api/authz/managers.py
moon_engine/api/orchestration/__init__.py
moon_engine/api/orchestration/managers.py
moon_engine/api/orchestration/pipeline.py
moon_engine/api/orchestration/slave.py
moon_engine/api/pipeline/__init__.py
moon_engine/api/pipeline/authz.py
moon_engine/api/pipeline/update.py
moon_engine/api/pipeline/update_pipeline.py
moon_engine/api/pipeline/validator.py
moon_engine/api/wrapper/__init__.py
moon_engine/api/wrapper/router.py
moon_engine/api/wrapper/update_wrapper.py
moon_engine/api/wrapper/api/__init__.py
moon_engine/api/wrapper/api/authz.py
moon_engine/api/wrapper/api/pipeline.py
moon_engine/api/wrapper/api/update.py
moon_engine/plugins/__init__.py
moon_engine/plugins/authz.py
moon_engine/plugins/oslowrapper.py
moon_engine/plugins/pyorchestrator.py
moon_engine-0.8.dist-info/LICENSE
moon_engine-0.8.dist-info/METADATA
moon_engine-0.8.dist-info/WHEEL
moon_engine-0.8.dist-info/entry_points.txt
moon_engine-0.8.dist-info/top_level.txt
moon_engine-0.8.dist-info/RECORD
