Metadata-Version: 2.1
Name: moon-engine
Version: 0.8
Summary: UNKNOWN
Home-page: UNKNOWN
Author: Thomas Duval
Author-email: thomas.duval@orange.com
License: UNKNOWN
Platform: UNKNOWN
Classifier: Programming Language :: Python
Classifier: Development Status :: 1 - Planning
Classifier: License :: OSI Approved
Classifier: Natural Language :: French
Classifier: Operating System :: OS Independent
Classifier: Programming Language :: Python :: 3
Requires-Dist: hug
Requires-Dist: pyaml
Requires-Dist: moon-utilities
Requires-Dist: moon-cache
Requires-Dist: gunicorn
Requires-Dist: sqlalchemy
Requires-Dist: pymysql
